{"skeleton":{"hash":"k5Esv2TIn2kdTlaXf7wleUZh2as","spine":"3.8.99","x":-113,"y":-99,"width":225,"height":215,"images":"","audio":"D:/works/Gadgame/Ladder Run/alien ascent/stand-trap"},"bones":[{"name":"root"},{"name":"pivot","parent":"root"},{"name":"spike-ball-pivot","parent":"pivot","y":5},{"name":"spike-ball","parent":"spike-ball-pivot"}],"slots":[{"name":"purple-glow","bone":"spike-ball","attachment":"purple-glow","blend":"additive"},{"name":"spike-ball","bone":"spike-ball","attachment":"spike-ball"}],"skins":[{"name":"default","attachments":{"purple-glow":{"purple-glow":{"x":-0.5,"y":3.5,"width":225,"height":215}},"spike-ball":{"spike-ball":{"x":-1,"y":3,"width":166,"height":154}}}}],"animations":{"idle":{"slots":{"purple-glow":{"color":[{"color":"ffffffff","curve":0.25,"c3":0.75},{"time":0.4,"color":"ffffff9c","curve":0.25,"c3":0.75},{"time":0.8,"color":"ffffffff"}]}},"bones":{"spike-ball":{"rotate":[{"angle":1.31,"curve":0.375,"c2":0.5,"c3":0.75},{"time":0.2,"angle":3.81,"curve":0.25,"c3":0.75},{"time":0.6,"angle":-1.19,"curve":0.25,"c3":0.625,"c4":0.5},{"time":0.8,"angle":1.31}],"translate":[{"curve":0.25,"c3":0.75},{"time":0.4,"y":2.28,"curve":0.25,"c3":0.75},{"time":0.8}],"scale":[{"curve":0.25,"c3":0.75},{"time":0.2667,"x":0.973,"y":0.973,"curve":0.25,"c3":0.75},{"time":0.5333,"x":1.05,"y":1.05,"curve":0.25,"c3":0.75},{"time":0.8}]}}}}}